langchain_valyu/__init__.py
langchain_valyu/_utilities.py
langchain_valyu/py.typed
langchain_valyu/retrievers.py
langchain_valyu/tools.py
langchain_valyu-0.3.5.dist-info/METADATA
langchain_valyu-0.3.5.dist-info/WHEEL
langchain_valyu-0.3.5.dist-info/licenses/LICENSE
langchain_valyu-0.3.5.dist-info/RECORD
