Metadata-Version: 2.4
Name: langchain-valyu
Version: 0.3.5
Summary: An integration package connecting Valyu and LangChain
License: MIT
License-File: LICENSE
Requires-Python: >=3.9,<4.0
Classifier: License :: OSI Approved :: MIT License
Classifier: Programming Language :: Python :: 3
Classifier: Programming Language :: Python :: 3.9
Classifier: Programming Language :: Python :: 3.10
Classifier: Programming Language :: Python :: 3.11
Classifier: Programming Language :: Python :: 3.12
Classifier: Programming Language :: Python :: 3.13
Classifier: Programming Language :: Python :: 3.14
Requires-Dist: langchain-core (>=0.3.54,<0.4.0)
Requires-Dist: valyu (>=2.0.2,<3.0.0)
Project-URL: Repository, https://github.com/langchain-ai/langchain
Project-URL: Release Notes, https://github.com/langchain-ai/langchain/releases?q=tag%3A%22valyu%3D%3D0%22&expanded=true
Project-URL: Source Code, https://github.com/langchain-ai/langchain/tree/master/libs/partners/valyu
